mohit/__init__.py
mohit-0.1.1.dist-info/METADATA
mohit-0.1.1.dist-info/WHEEL
mohit-0.1.1.dist-info/top_level.txt
mohit-0.1.1.dist-info/RECORD
